setup.py
jf_distributions/Binomialdistribution.py
jf_distributions/Gaussiandistribution.py
jf_distributions/Generaldistribution.py
jf_distributions/__init__.py
jf_distributions.egg-info/PKG-INFO
jf_distributions.egg-info/SOURCES.txt
jf_distributions.egg-info/dependency_links.txt
jf_distributions.egg-info/not-zip-safe
jf_distributions.egg-info/top_level.txt