Metadata-Version: 1.0
Name: jf-distributions
Version: 0.1
Summary: Gaussian and Binomial distributions
Home-page: UNKNOWN
Author: Jesse Fredrickson
Author-email: jfreds@bu.edu
License: UNKNOWN
Platform: UNKNOWN
